hidefix-0.12.0.dist-info/METADATA
hidefix-0.12.0.dist-info/WHEEL
hidefix-0.12.0.dist-info/entry_points.txt
hidefix-0.12.0.dist-info/license_files/LICENSE
hidefix/__init__.py
hidefix/xarray.py
hidefix/hidefix.abi3.so
hidefix-0.12.0.dist-info/RECORD
