Metadata-Version: 2.1
Name: hidefix
Version: 0.12.0
Classifier: Programming Language :: Rust
Classifier: Programming Language :: Python :: Implementation :: CPython
Classifier: Programming Language :: Python :: Implementation :: PyPy
Requires-Dist: numpy
Requires-Dist: xarray >=2023
Requires-Dist: netCDF4
License-File: LICENSE
Summary: Concurrent HDF5 and NetCDF4 reader (experimental)
Keywords: hdf,async,concurrency
Author: Gaute Hope <eg@gaute.vetsj.com>
Author-email: Gaute Hope <eg@gaute.vetsj.com>
License: LGPL-3.0-or-later
Requires-Python: >=3.9
Project-URL: Source Code, https://github.com/gauteh/hidefix
